glmnet/__init__.py
glmnet/_bootstrap.py
glmnet/_elnet_point.cpython-39-x86_64-linux-gnu.so
glmnet/_fishnet.cpython-39-x86_64-linux-gnu.so
glmnet/_gaussnet.cpython-39-x86_64-linux-gnu.so
glmnet/_lognet.cpython-39-x86_64-linux-gnu.so
glmnet/_multigaussnet.cpython-39-x86_64-linux-gnu.so
glmnet/_utils.py
glmnet/_version.py
glmnet/base.py
glmnet/cox.py
glmnet/data.py
glmnet/elnet.py
glmnet/family.py
glmnet/glm.py
glmnet/glmnet.py
glmnet/inference.py
glmnet/irls.py
glmnet/regularized_glm.py
glmnet/scorer.py
glmnet/scoring.py
glmnet/paths/__init__.py
glmnet/paths/fastnet.py
glmnet/paths/fishnet.py
glmnet/paths/gaussnet.py
glmnet/paths/lognet.py
glmnet/paths/multiclassnet.py
glmnet/paths/multigaussnet.py
glmnet/test_data/test_001.pickle
glmnet/test_data/test_002.pickle
glmnet/test_data/test_003.pickle
glmnet/test_data/test_004.pickle
glmnet/test_data/test_005.pickle
glmnet/test_data/test_006.pickle
glmnet/test_data/test_007.pickle
glmnet/test_data/test_008.pickle
glmnet/test_data/test_009.pickle
glmnet/test_data/test_010.pickle
glmnet/test_data/test_011.pickle
glmnet/test_data/test_012.pickle
glmnet/test_data/test_013.pickle
glmnet/test_data/test_014.pickle
glmnet/test_data/test_015.pickle
glmnet/test_data/test_016.pickle
glmnet/test_data/test_017.pickle
glmnet/test_data/test_018.pickle
glmnet/test_data/test_019.pickle
glmnet/test_data/test_020.pickle
glmnet/test_data/test_021.pickle
glmnet/test_data/test_022.pickle
glmnet/test_data/test_023.pickle
glmnet/test_data/test_024.pickle
glmnet/test_data/test_025.pickle
glmnet/test_data/test_026.pickle
glmnet/test_data/test_027.pickle
glmnet/test_data/test_028.pickle
glmnet/test_data/test_029.pickle
glmnet/test_data/test_030.pickle
glmnet/test_data/test_031.pickle
glmnet/test_data/test_032.pickle
glmnet/test_data/test_033.pickle
glmnet/test_data/test_034.pickle
glmnet/test_data/test_035.pickle
glmnet/test_data/test_036.pickle
glmnet/test_data/test_037.pickle
glmstar-0.1.1.dist-info/METADATA
glmstar-0.1.1.dist-info/WHEEL
glmstar-0.1.1.dist-info/top_level.txt
glmstar-0.1.1.dist-info/RECORD
glmstar-0.1.1.dist-info/licenses/LICENSE.txt
