Metadata-Version: 2.4
Name: glmstar
Version: 0.1.1
Summary: GlmNet for Python
Author-email: Trevor Hastie <hastie@stanford.edu>, Jonathan Taylor <jonathan.taylor@stanford.edu>, James Yang <jamesyang916@gmail.com>, Balasubramanian Narasimhan <naras@stanford.edu>
Maintainer-email: Jonathan Taylor <jonathan.taylor@stanford.edu>
License-Expression: BSD-3-Clause
Classifier: Development Status :: 3 - Alpha
Classifier: Environment :: Console
Classifier: Intended Audience :: Science/Research
Classifier: Operating System :: OS Independent
Classifier: Programming Language :: Python
Classifier: Topic :: Scientific/Engineering
Requires-Python: >=3.9
License-File: LICENSE.txt
Requires-Dist: numpy
Requires-Dist: scipy<1.16.0,>=1.8
Requires-Dist: pandas
Requires-Dist: scikit-learn>=1.2
Requires-Dist: joblib
Requires-Dist: statsmodels>=0.13
Requires-Dist: coxdev
Requires-Dist: pybind11
Requires-Dist: tqdm
Requires-Dist: mpmath
Dynamic: license-file
